test_pypi_usamuru/__init__.py
test_pypi_usamuru/m_mod_usamuru.py
test_pypi_usamuru-0.0.1.dist-info/LICENSE.txt
test_pypi_usamuru-0.0.1.dist-info/METADATA
test_pypi_usamuru-0.0.1.dist-info/WHEEL
test_pypi_usamuru-0.0.1.dist-info/top_level.txt
test_pypi_usamuru-0.0.1.dist-info/RECORD
