Metadata-Version: 2.1
Name: test-pypi-usamuru
Version: 0.0.1
Summary: my test package
Author-email: Usamuru <maciejgrodzki.py@gmail.com>
License: MIT License
Keywords: test_pypi_usamuru,name,surname,funfunction
Classifier: Environment :: GPU :: NVIDIA CUDA :: 11.6
Classifier: Environment :: MacOS X :: Carbon
Requires-Python: >=3.0
License-File: LICENSE.txt
Requires-Dist: numpy
